vllm_client/__init__.py
vllm_client/async_client.py
vllm_client/sampling_params.py
vllm_client-0.3.2.0.dist-info/LICENSE
vllm_client-0.3.2.0.dist-info/METADATA
vllm_client-0.3.2.0.dist-info/WHEEL
vllm_client-0.3.2.0.dist-info/top_level.txt
vllm_client-0.3.2.0.dist-info/RECORD
