Metadata-Version: 2.1
Name: vllm-client
Version: 0.3.2.0
Summary: Client for the vLLM API with minimal dependencies
Home-page: https://github.com/viktor-ferenczi/vllm-client
Author: Viktor Ferenczi
License: Apache 2.0
Project-URL: Homepage, https://github.com/viktor-ferenczi/vllm-client
Project-URL: Documentation, https://github.com/viktor-ferenczi/vllm-client
Platform: UNKNOWN
Classifier: Programming Language :: Python :: 3.8
Classifier: Programming Language :: Python :: 3.9
Classifier: Programming Language :: Python :: 3.10
Classifier: Programming Language :: Python :: 3.11
Classifier: Programming Language :: Python :: 3.12
Classifier: License :: OSI Approved :: Apache Software License
Classifier: Topic :: Scientific/Engineering :: Artificial Intelligence
Requires-Python: >=3.8
License-File: LICENSE
Requires-Dist: aiohttp
